{
	"info": {
		"_postman_id": "ffb6d38b-20cc-42fe-a885-949735cd1ab8",
		"name": "Assignment 2 mysql Expressjs item",
		"schema": "https://schema.getpostman.com/json/collection/v2.1.0/collection.json",
		"_exporter_id": "20920905"
	},
	"item": [
		{
			"name": "getAll",
			"request": {
				"method": "GET",
				"header": []
			},
			"response": []
		},
		{
			"name": "Delete",
			"request": {
				"method": "DELETE",
				"header": [],
				"url": {
					"raw": ""
				}
			},
			"response": []
		},
		{
			"name": "update",
			"request": {
				"method": "PUT",
				"header": [],
				"url": {
					"raw": ""
				}
			},
			"response": []
		},
		{
			"name": "Post",
			"request": {
				"method": "POST",
				"header": [],
				"url": {
					"raw": ""
				}
			},
			"response": []
		},
		{
			"name": "Search",
			"request": {
				"method": "GET",
				"header": [],
				"url": {
					"raw": ""
				}
			},
			"response": []
		}
	]
}